MANIFEST.in
requirements.txt
setup.cfg
setup.py
test-requirements.txt
opencontrail_kubelet/__init__.py
opencontrail_kubelet/lxc_manager.py
opencontrail_kubelet/plugin.py
opencontrail_kubelet/shell.py
opencontrail_kubelet/vrouter_api.py
opencontrail_kubelet.egg-info/PKG-INFO
opencontrail_kubelet.egg-info/SOURCES.txt
opencontrail_kubelet.egg-info/dependency_links.txt
opencontrail_kubelet.egg-info/entry_points.txt
opencontrail_kubelet.egg-info/requires.txt
opencontrail_kubelet.egg-info/top_level.txt
opencontrail_kubelet/tests/__init__.py