Metadata-Version: 1.0
Name: opencontrail-kubelet
Version: 0.3.4
Summary: OpenContrail kubelet plugin
Home-page: http://www.opencontrail.org/
Author: OpenContrail
Author-email: dev@lists.opencontrail.org
License: Apache Software License
Platform: UNKNOWN
